LICENSE
MANIFEST.in
README.rst
setup.cfg
setup.py
allabaster/__init__.py
allabaster/__init__.pyc
allabaster/_version.py
allabaster/_version.pyc
allabaster/about.html
allabaster/donate.html
allabaster/layout.html
allabaster/navigation.html
allabaster/relations.html
allabaster/support.py
allabaster/theme.conf
allabaster.egg-info/PKG-INFO
allabaster.egg-info/SOURCES.txt
allabaster.egg-info/dependency_links.txt
allabaster.egg-info/top_level.txt
allabaster/static/alabaster.css_t
allabaster/static/custom.css