Metadata-Version: 1.1
Name: allabaster
Version: 0.1.0
Summary: An embeddable Sphinx theme, based on Alabaster.
Home-page: https://allabaster.readthedocs.io
Author: Alexander Artemenko
Author-email: svetlyak.40wt@gmail.com
License: UNKNOWN
Platform: UNKNOWN
Classifier: Intended Audience :: Developers
Classifier: License :: OSI Approved :: BSD License
Classifier: Operating System :: OS Independent
Classifier: Topic :: Documentation
Classifier: Topic :: Software Development :: Documentation
Classifier: Programming Language :: Python
Classifier: Programming Language :: Python :: 2.6
Classifier: Programming Language :: Python :: 2.7
Classifier: Programming Language :: Python :: 3.2
Classifier: Programming Language :: Python :: 3.3
Classifier: Programming Language :: Python :: 3.4
